LICENSE
MANIFEST.in
README.rst
pyproject.toml
setup.cfg
setup.py
django_polls_carrycooldude.egg-info/PKG-INFO
django_polls_carrycooldude.egg-info/SOURCES.txt
django_polls_carrycooldude.egg-info/dependency_links.txt
django_polls_carrycooldude.egg-info/requires.txt
django_polls_carrycooldude.egg-info/top_level.txt
mysite/__init__.py
mysite/asgi.py
mysite/settings.py
mysite/urls.py
mysite/wsgi.py
polls/__init__.py
polls/admin.py
polls/apps.py
polls/models.py
polls/tests.py
polls/urls.py
polls/views.py
polls/migrations/0001_initial.py
polls/migrations/__init__.py
polls/static/polls/style.css
polls/static/polls/images/background.png
polls/templates/admin/base_site.html
polls/templates/polls/detail.html
polls/templates/polls/index.html
polls/templates/polls/results.html